angou_okex/__init__.py
angou_okex/rest.py
angou_okex-1.dist-info/LICENSE.txt
angou_okex-1.dist-info/METADATA
angou_okex-1.dist-info/RECORD
angou_okex-1.dist-info/WHEEL
angou_okex-1.dist-info/top_level.txt
